{
  "timestamp": "2026-02-11T17:01:27.931030",
  "promoted": [
    "R010",
    "R012",
    "R013",
    "R014"
  ],
  "killed": [],
  "parked": [],
  "summary": "\nRBI Pipeline Summary \u2014 2026-02-11\n============================================================\nScreened: 4 ideas\nPromoted: 4 (R010, R012, R013, R014)\nKilled: 0 (none)\nParked: 0 (none)\n\nPROMOTED IDEAS (ready for full hypothesis):\n  R010 \u2014 Multi-Asset Momentum\n    PF: 1.62 gross | Trades: 82 | Sharpe: 1.15\n    Params: {'roc_period': 30, 'min_roc': 1.0, 'stop_pct': 2.0, 'target_pct': 12.0, 'aux_data_dir': '/Users/siphokhoza/ai-chief-of-staff/data', 'aux_timeframe_hours': 4, 'long_only': True}\n\n  R012 \u2014 Adaptive Momentum Burst (AMB)\n    PF: 1.66 gross | Trades: 35 | Sharpe: 0.65\n    Params: {'bb_period': 20, 'bb_std': 2.0, 'squeeze_lookback': 50, 'squeeze_pct': 20, 'min_squeeze_bars': 3, 'ma_period': 50, 'ma_slope_bars': 5, 'stop_pct': 2.0, 'target_pct': 12.0}\n\n  R013 \u2014 Acceleration Breakout Filter (ABF)\n    PF: 2.34 gross | Trades: 35 | Sharpe: 0.87\n    Params: {'channel_period': 30, 'roc_short': 5, 'roc_long': 15, 'stop_pct': 2.0, 'target_pct': 12.0}\n\n  R014 \u2014 Multi-Timeframe Breakout Confluence (MTBC)\n    PF: 1.39 gross | Trades: 107 | Sharpe: 1.16\n    Params: {'channel_period': 15, 'trend_ma_period': 90, 'stop_pct': 4.0, 'target_pct': 6.0}\n",
  "screens": [
    {
      "idea_id": "R010",
      "idea_name": "Multi-Asset Momentum",
      "archetype": "multi_asset_momentum",
      "params": {
        "roc_period": 30,
        "min_roc": 1.0,
        "stop_pct": 2.0,
        "target_pct": 12.0,
        "aux_data_dir": "/Users/siphokhoza/ai-chief-of-staff/data",
        "aux_timeframe_hours": 4,
        "long_only": true
      },
      "timeframe": "4H",
      "data_bars": 6571,
      "data_period": "2023-02-08 \u2192 2026-02-07",
      "gross_pf": 1.62,
      "net_pf": 1.53,
      "win_rate": 0.244,
      "total_trades": 82,
      "expectancy_gross": 642.88,
      "expectancy_net": 577.19,
      "sharpe": 1.15,
      "sortino": 99.0,
      "max_dd": 17737.36,
      "max_dd_duration_days": 199.0,
      "avg_duration_hours": 134.4,
      "buy_hold_pnl": 47039.94,
      "strategy_pnl_gross": 52715.89,
      "strategy_pnl_net": 47329.35,
      "total_costs": 5386.54,
      "cost_pct": 0.1,
      "verdict": "promote",
      "reason": "Gross PF 1.62 >= 1.3 threshold. Promote to full hypothesis.",
      "timestamp": "2026-02-11T16:54:15.807108"
    },
    {
      "idea_id": "R012",
      "idea_name": "Adaptive Momentum Burst (AMB)",
      "archetype": "adaptive_momentum_burst",
      "params": {
        "bb_period": 20,
        "bb_std": 2.0,
        "squeeze_lookback": 50,
        "squeeze_pct": 20,
        "min_squeeze_bars": 3,
        "ma_period": 50,
        "ma_slope_bars": 5,
        "stop_pct": 2.0,
        "target_pct": 12.0
      },
      "timeframe": "4H",
      "data_bars": 6571,
      "data_period": "2023-02-08 \u2192 2026-02-07",
      "gross_pf": 1.66,
      "net_pf": 1.56,
      "win_rate": 0.229,
      "total_trades": 35,
      "expectancy_gross": 738.11,
      "expectancy_net": 666.34,
      "sharpe": 0.65,
      "sortino": 99.0,
      "max_dd": 12399.97,
      "max_dd_duration_days": 194.0,
      "avg_duration_hours": 148.0,
      "buy_hold_pnl": 47039.94,
      "strategy_pnl_gross": 25833.69,
      "strategy_pnl_net": 23321.8,
      "total_costs": 2511.89,
      "cost_pct": 0.1,
      "verdict": "promote",
      "reason": "Gross PF 1.66 >= 1.3 threshold. Promote to full hypothesis.",
      "timestamp": "2026-02-11T16:59:39.328118"
    },
    {
      "idea_id": "R013",
      "idea_name": "Acceleration Breakout Filter (ABF)",
      "archetype": "acceleration_breakout",
      "params": {
        "channel_period": 30,
        "roc_short": 5,
        "roc_long": 15,
        "stop_pct": 2.0,
        "target_pct": 12.0
      },
      "timeframe": "4H",
      "data_bars": 6571,
      "data_period": "2023-02-08 \u2192 2026-02-07",
      "gross_pf": 2.34,
      "net_pf": 2.21,
      "win_rate": 0.257,
      "total_trades": 35,
      "expectancy_gross": 1140.22,
      "expectancy_net": 1081.12,
      "sharpe": 0.87,
      "sortino": 99.0,
      "max_dd": 9368.43,
      "max_dd_duration_days": 202.0,
      "avg_duration_hours": 92.0,
      "buy_hold_pnl": 47039.94,
      "strategy_pnl_gross": 39907.74,
      "strategy_pnl_net": 37839.18,
      "total_costs": 2068.56,
      "cost_pct": 0.1,
      "verdict": "promote",
      "reason": "Gross PF 2.34 >= 1.3 threshold. Promote to full hypothesis.",
      "timestamp": "2026-02-11T17:00:44.362187"
    },
    {
      "idea_id": "R014",
      "idea_name": "Multi-Timeframe Breakout Confluence (MTBC)",
      "archetype": "mtf_breakout",
      "params": {
        "channel_period": 15,
        "trend_ma_period": 90,
        "stop_pct": 4.0,
        "target_pct": 6.0
      },
      "timeframe": "4H",
      "data_bars": 6571,
      "data_period": "2023-02-08 \u2192 2026-02-07",
      "gross_pf": 1.39,
      "net_pf": 1.33,
      "win_rate": 0.505,
      "total_trades": 107,
      "expectancy_gross": 536.48,
      "expectancy_net": 470.35,
      "sharpe": 1.16,
      "sortino": 99.0,
      "max_dd": 26970.89,
      "max_dd_duration_days": 360.0,
      "avg_duration_hours": 128.7,
      "buy_hold_pnl": 47039.94,
      "strategy_pnl_gross": 57403.43,
      "strategy_pnl_net": 50327.36,
      "total_costs": 7076.06,
      "cost_pct": 0.1,
      "verdict": "promote",
      "reason": "Gross PF 1.39 >= 1.3 threshold. Promote to full hypothesis.",
      "timestamp": "2026-02-11T17:01:05.140050"
    }
  ]
}